synthesis/ALU.sv
`timescale 1ns/1ps

module ALU(
  input logic [31:0]    operandA,
  input logic [31:0]    operandB,
  input CTRL::alu_op_t  aluOp,
  
  output logic [31:0]   result,
  output logic          zero,
  output logic          negative,
  output logic          carry,
  output logic          overflow
);

    logic [32:0] resultAux;
    always_comb begin
      case (aluOp)
        CTRL::ADDalu:   resultAux = operandA + operandB;         
        CTRL::SUBalu:   resultAux = operandA - operandB;         
        CTRL::ANDalu:   resultAux = operandA & operandB;         
        CTRL::ORalu:    resultAux = operandA | operandB;         
        CTRL::XORalu:   resultAux = operandA ^ operandB;         
        CTRL::SLLalu:   resultAux = operandA << operandB[4:0];   
        CTRL::SRLalu:   resultAux = operandA >> operandB[4:0];   
        CTRL::SRAalu:   resultAux = $signed(operandA) >>> operandB[4:0]; 
        CTRL::LUIalu:   resultAux = operandB << 12;
        CTRL::AUIPCalu: resultAux = operandA + (operandB << 12);
        CTRL::JALRalu:  resultAux = (operandA + operandB) & ~(32'b1);                    
        default: resultAux = 33'b0;
      endcase
    end

    assign result = resultAux[31:0];
    assign carry = resultAux[32];
    assign zero = ~|result;
    assign negative = result[31];
    assign overflow = (~operandA[31] & ~operandB[31] & result[31])|(operandA[31] & operandB[31] & ~result[31]) ;

endmodule

synthesis/tb/tb_ALU.sv
`timescale 1ns/1ps

module tb_ALU;

    logic [31:0] operandA;
    logic [31:0] operandB;
    CTRL::alu_op_t aluOp;

    logic [31:0] result;
    logic zero;
    logic negative;
    logic carry;
    logic overflow;

    ALU dut(
        .operandA(operandA),
        .operandB(operandB),
        .aluOp(aluOp),
        .result(result),
        .zero(zero),
        .negative(negative),
        .carry(carry),
        .overflow(overflow)
    );

    task check_result(
        input [31:0] expected
    );
    begin
        #1;

        if(result !== expected) begin
            $display("FAIL @ %0t", $time);
            $display("  A        = %h", operandA);
            $display("  B        = %h", operandB);
            $display("  Result   = %h", result);
            $display("  Expected = %h", expected);
        end
        else begin
            $display("PASS @ %0t", $time);
        end
    end
    endtask

    initial begin

        $dumpfile("alu.vcd");
        $dumpvars(0,tb_ALU);

        //--------------------------------------------------
        // ADD
        //--------------------------------------------------

        operandA = 10;
        operandB = 20;
        aluOp    = CTRL::ADDalu;
        check_result(30);

        operandA = 32'hFFFFFFFF;
        operandB = 1;
        aluOp    = CTRL::ADDalu;
        check_result(0);

        //--------------------------------------------------
        // SUB
        //--------------------------------------------------

        operandA = 50;
        operandB = 20;
        aluOp    = CTRL::SUBalu;
        check_result(30);

        operandA = 20;
        operandB = 50;
        aluOp    = CTRL::SUBalu;
        check_result(32'hFFFFFFE2);

        //--------------------------------------------------
        // AND
        //--------------------------------------------------

        operandA = 32'hF0F0F0F0;
        operandB = 32'h0FF00FF0;
        aluOp    = CTRL::ANDalu;
        check_result(32'h00F000F0);

        //--------------------------------------------------
        // OR
        //--------------------------------------------------

        operandA = 32'hF0F0F0F0;
        operandB = 32'h0FF00FF0;
        aluOp    = CTRL::ORalu;
        check_result(32'hFFF0FFF0);

        //--------------------------------------------------
        // XOR
        //--------------------------------------------------

        operandA = 32'hAAAA5555;
        operandB = 32'hFFFF0000;
        aluOp    = CTRL::XORalu;
        check_result(32'h55555555);

        //--------------------------------------------------
        // SLL
        //--------------------------------------------------

        operandA = 1;
        operandB = 4;
        aluOp    = CTRL::SLLalu;
        check_result(16);

        //--------------------------------------------------
        // SRL
        //--------------------------------------------------

        operandA = 32'h80000000;
        operandB = 4;
        aluOp    = CTRL::SRLalu;
        check_result(32'h08000000);

        //--------------------------------------------------
        // SRA
        //--------------------------------------------------

        operandA = 32'h80000000;
        operandB = 4;
        aluOp    = CTRL::SRAalu;
        check_result(32'hF8000000);

        //--------------------------------------------------
        // LUI
        //--------------------------------------------------

        operandA = 0;
        operandB = 32'h12345;
        aluOp    = CTRL::LUIalu;
        check_result(32'h12345000);

        //--------------------------------------------------
        // AUIPC
        //--------------------------------------------------

        operandA = 32'h1000;
        operandB = 32'h10;
        aluOp    = CTRL::AUIPCalu;
        check_result(32'h11000);

        //--------------------------------------------------
        // JALR
        //--------------------------------------------------

        operandA = 100;
        operandB = 21;
        aluOp    = CTRL::JALRalu;
        check_result(120);

        //--------------------------------------------------
        // ZERO FLAG
        //--------------------------------------------------

        operandA = 1;
        operandB = 1;
        aluOp    = CTRL::SUBalu;

        #1;

        if(!zero)
            $display("FAIL ZERO FLAG");

        //--------------------------------------------------
        // NEGATIVE FLAG
        //--------------------------------------------------

        operandA = 1;
        operandB = 2;
        aluOp    = CTRL::SUBalu;

        #1;

        if(!negative)
            $display("FAIL NEGATIVE FLAG");

        //--------------------------------------------------
        // ADD OVERFLOW
        //--------------------------------------------------

        operandA = 32'h7FFFFFFF;
        operandB = 1;
        aluOp    = CTRL::ADDalu;

        #1;

        if(!overflow)
            $display("FAIL OVERFLOW FLAG");

        //--------------------------------------------------

        $display("TESTBENCH FINISHED");
        $finish;

    end

endmodule

synthesis/tests/alu.vcd
$date
	Fri Jun 12 03:23:35 2026
$end
$version
	Icarus Verilog
$end
$timescale
	1ps
$end
$scope module tb_ALU $end
$var wire 1 ! zero $end
$var wire 32 " result [31:0] $end
$var wire 1 # overflow $end
$var wire 1 $ negative $end
$var wire 1 % carry $end
$var reg 4 & aluOp [3:0] $end
$var reg 32 ' operandA [31:0] $end
$var reg 32 ( operandB [31:0] $end
$scope module dut $end
$var wire 4 ) aluOp [3:0] $end
$var wire 32 * operandA [31:0] $end
$var wire 32 + operandB [31:0] $end
$var wire 1 # overflow $end
$var wire 1 ! zero $end
$var wire 32 , result [31:0] $end
$var wire 1 $ negative $end
$var wire 1 % carry $end
$var reg 33 - resultAux [32:0] $end
$upscope $end
$scope task check_result $end
$var reg 32 . expected [31:0] $end
$upscope $end
$upscope $end
$enddefinitions $end
$comment Show the parameter values. $end
$dumpall
$end
#0
$dumpvars
b11110 .
b11110 -
b11110 ,
b10100 +
b1010 *
b0 )
b10100 (
b1010 '
b0 &
0%
0$
0#
b11110 "
0!
$end
#1000
1!
b0 "
b0 ,
1%
b100000000000000000000000000000000 -
b0 .
b1 (
b1 +
b11111111111111111111111111111111 '
b11111111111111111111111111111111 *
#2000
0!
b11110 "
b11110 ,
0%
b11110 -
b11110 .
b1 &
b1 )
b10100 (
b10100 +
b110010 '
b110010 *
#3000
1#
1$
b11111111111111111111111111100010 "
b11111111111111111111111111100010 ,
1%
b111111111111111111111111111100010 -
b11111111111111111111111111100010 .
b110010 (
b110010 +
b10100 '
b10100 *
#4000
0#
0$
b111100000000000011110000 "
b111100000000000011110000 ,
0%
b111100000000000011110000 -
b111100000000000011110000 .
b10 &
b10 )
b1111111100000000111111110000 (
b1111111100000000111111110000 +
b11110000111100001111000011110000 '
b11110000111100001111000011110000 *
#5000
1$
b11111111111100001111111111110000 "
b11111111111100001111111111110000 ,
b11111111111100001111111111110000 -
b11111111111100001111111111110000 .
b11 &
b11 )
#6000
1#
0$
b1010101010101010101010101010101 "
b1010101010101010101010101010101 ,
b1010101010101010101010101010101 -
b1010101010101010101010101010101 .
b100 &
b100 )
b11111111111111110000000000000000 (
b11111111111111110000000000000000 +
b10101010101010100101010101010101 '
b10101010101010100101010101010101 *
#7000
0#
b10000 "
b10000 ,
b10000 -
b10000 .
b101 &
b101 )
b100 (
b100 +
b1 '
b1 *
#8000
b1000000000000000000000000000 "
b1000000000000000000000000000 ,
b1000000000000000000000000000 -
b1000000000000000000000000000 .
b110 &
b110 )
b10000000000000000000000000000000 '
b10000000000000000000000000000000 *
#9000
1$
b11111000000000000000000000000000 "
b11111000000000000000000000000000 ,
1%
b111111000000000000000000000000000 -
b11111000000000000000000000000000 .
b111 &
b111 )
#10000
0$
b10010001101000101000000000000 "
b10010001101000101000000000000 ,
0%
b10010001101000101000000000000 -
b10010001101000101000000000000 .
b1000 &
b1000 )
b10010001101000101 (
b10010001101000101 +
b0 '
b0 *
#11000
b10001000000000000 "
b10001000000000000 ,
b10001000000000000 -
b10001000000000000 .
b1001 &
b1001 )
b10000 (
b10000 +
b1000000000000 '
b1000000000000 *
#12000
b1111000 "
b1111000 ,
b1111000 -
b1111000 .
b1010 &
b1010 )
b10101 (
b10101 +
b1100100 '
b1100100 *
#13000
1!
b0 "
b0 ,
b0 -
b1 &
b1 )
b1 (
b1 +
b1 '
b1 *
#14000
1#
1$
0!
b11111111111111111111111111111111 "
b11111111111111111111111111111111 ,
1%
b111111111111111111111111111111111 -
b10 (
b10 +
#15000
b10000000000000000000000000000000 "
b10000000000000000000000000000000 ,
0%
b10000000000000000000000000000000 -
b0 &
b0 )
b1 (
b1 +
b1111111111111111111111111111111 '
b1111111111111111111111111111111 *
