synthesis/REGBank.sv
`timescale 1ns/1ps

module REGBank(
  input  logic        clock,
  input  logic        reset,
  input  logic        REGwrite,
  input  logic [4:0]  rs1,
  input  logic [4:0]  rs2,
  input  logic [4:0]  rd,
  input  logic [31:0] DATAwrite,
  
  output logic [31:0] Data_A,
  output logic [31:0] Data_B
);
    logic [31:0] regs [31:0];

    assign Data_A = regs[rs1];
    assign Data_B = regs[rs2];
    integer i;
    
    always_ff @(posedge clock) begin
      if (reset) begin
        for(i=0;i<32;i = i+1) begin
          regs[i] <= 32'b0;
        end
      end 
      if (REGwrite) begin
        regs[rd] <= DATAwrite;
      end
      regs[0] <= 32'b0;
    end
endmodule

synthesis/tb/tb_REGBank.sv
`timescale 1ns/1ps

module tb_REGBank;

    logic        clock;
    logic        reset;
    logic        REGwrite;

    logic [4:0]  rs1;
    logic [4:0]  rs2;
    logic [4:0]  rd;

    logic [31:0] DATAwrite;

    logic [31:0] Data_A;
    logic [31:0] Data_B;

    REGBank dut(
        .clock(clock),
        .reset(reset),
        .REGwrite(REGwrite),
        .rs1(rs1),
        .rs2(rs2),
        .rd(rd),
        .DATAwrite(DATAwrite),
        .Data_A(Data_A),
        .Data_B(Data_B)
    );

    //--------------------------------------------------
    // clock generation
    //--------------------------------------------------

    always #5 clock = ~clock;
    //--------------------------------------------------
    // helper task
    //--------------------------------------------------

    task check(
        input [31:0] actual,
        input [31:0] expected,
        input [255:0] message,
        input REGWrite,
        input [31:0] Data_A,
        input [31:0] Data_B
    );
    begin
        if(actual !== expected) begin
            $display("FAIL: %s", message);
            $display("  expected = %h", expected);
            $display("  actual   = %h", actual);
            $display("Data_A: %h, Data_B: %h, REGWrite: %h", Data_A, Data_B, REGWrite);
        end
        else begin
            $display("PASS: %s", message);
        end
    end
    endtask

    //--------------------------------------------------
    // test sequence
    //--------------------------------------------------

    initial begin

        $dumpfile("tests/regbank.vcd");
        $dumpvars(0,tb_REGBank);

        clock     = 0;
        reset     = 0;
        REGwrite  = 0;
        rs1       = 0;
        rs2       = 0;
        rd        = 0;
        DATAwrite = 0;

        //--------------------------------------------------
        // RESET
        //--------------------------------------------------

        @(negedge clock);
        reset = 1;
    
        @(posedge clock);
        @(negedge clock);

        reset = 0;

        rs1 = 5;
        rs2 = 10;

        #5;

        check(Data_A, 0, "reset clears register 5", REGwrite, Data_A, Data_B);
        check(Data_B, 0, "reset clears register 10", REGwrite, Data_A, Data_B);

        //--------------------------------------------------
        // WRITE x5
        //--------------------------------------------------
        @(negedge clock);

        rd        = 5;
        DATAwrite = 32'h12345678;
        REGwrite  = 1;

        @(posedge clock);
        @(negedge clock);

        REGwrite = 0;

        rs1 = 5;

        #5;

        check(Data_A,
              32'h12345678,
              "write/read register x5", REGwrite, Data_A, Data_B);

        //--------------------------------------------------
        // WRITE x10
        //--------------------------------------------------
        @(negedge clock);

        rd        = 10;
        DATAwrite = 32'hCAFEBABE;
        REGwrite  = 1;

        @(posedge clock);
        @(negedge clock);

        REGwrite = 0;

        rs2 = 10;

        #5;

        check(Data_B,
              32'hCAFEBABE,
              "write/read register x10", REGwrite, Data_A, Data_B);

        //--------------------------------------------------
        // VERIFY x5 STILL OK
        //--------------------------------------------------
        @(negedge clock);

        rs1 = 5;

        #5;

        check(Data_A,
              32'h12345678,
              "x5 preserved", REGwrite, Data_A, Data_B);

        //--------------------------------------------------
        // x0 MUST STAY ZERO
        //--------------------------------------------------
        @(negedge clock);

        rd        = 0;
        DATAwrite = 32'hFFFFFFFF;
        REGwrite  = 1;

        @(posedge clock);
        @(negedge clock);

        REGwrite = 0;

        rs1 = 0;

        #5;

        check(Data_A,
              32'h00000000,
              "x0 remains zero", REGwrite, Data_A, Data_B);

        //--------------------------------------------------
        // OVERWRITE x5
        //--------------------------------------------------
        @(negedge clock);

        rd        = 5;
        DATAwrite = 32'hDEADBEEF;
        REGwrite  = 1;

        @(posedge clock);
        @(negedge clock);

        REGwrite = 0;

        rs1 = 5;

        #5;

        check(Data_A,
              32'hDEADBEEF,
              "overwrite x5", REGwrite, Data_A, Data_B);

        //--------------------------------------------------
        // RESET AGAIN
        //--------------------------------------------------
        @(negedge clock);

        reset = 1;

        @(posedge clock);
        @(negedge clock);

        reset = 0;

        rs1 = 5;
        rs2 = 10;

        #5;

        check(Data_A,
              32'h00000000,
              "reset clears x5", REGwrite, Data_A, Data_B);

        check(Data_B,
              32'h00000000,
              "reset clears x10", REGwrite, Data_A, Data_B);

        //--------------------------------------------------

        $display("REGBank tests completed.");

        #10;
        $finish;

    end

endmodule

synthesis/tests/regbank.vcd
$date
	Wed Jun 17 06:08:14 2026
$end
$version
	Icarus Verilog
$end
$timescale
	1ps
$end
$scope module tb_REGBank $end
$var wire 32 ! Data_B [31:0] $end
$var wire 32 " Data_A [31:0] $end
$var reg 32 # DATAwrite [31:0] $end
$var reg 1 $ REGwrite $end
$var reg 1 % clock $end
$var reg 5 & rd [4:0] $end
$var reg 1 ' reset $end
$var reg 5 ( rs1 [4:0] $end
$var reg 5 ) rs2 [4:0] $end
$scope module dut $end
$var wire 32 * DATAwrite [31:0] $end
$var wire 32 + Data_A [31:0] $end
$var wire 32 , Data_B [31:0] $end
$var wire 1 $ REGwrite $end
$var wire 1 % clock $end
$var wire 5 - rd [4:0] $end
$var wire 1 ' reset $end
$var wire 5 . rs1 [4:0] $end
$var wire 5 / rs2 [4:0] $end
$var integer 32 0 i [31:0] $end
$upscope $end
$scope task check $end
$var reg 32 1 Data_A [31:0] $end
$var reg 32 2 Data_B [31:0] $end
$var reg 1 3 REGWrite $end
$var reg 32 4 actual [31:0] $end
$var reg 32 5 expected [31:0] $end
$var reg 256 6 message [255:0] $end
$upscope $end
$upscope $end
$enddefinitions $end
$comment Show the parameter values. $end
$dumpall
$end
#0
$dumpvars
bx 6
bx 5
bx 4
x3
bx 2
bx 1
bx 0
b0 /
b0 .
b0 -
bx ,
bx +
b0 *
b0 )
b0 (
0'
b0 &
0%
0$
b0 #
bx "
bx !
$end
#5000
b0 "
b0 +
b0 !
b0 ,
1%
#10000
1'
0%
#15000
b100000 0
1%
#20000
b1010 )
b1010 /
b101 (
b101 .
0'
0%
#25000
b0 2
b0 1
03
b11100100110010101110011011001010111010000100000011000110110110001100101011000010111001001110011001000000111001001100101011001110110100101110011011101000110010101110010001000000011000100110000 6
b0 5
b0 4
1%
#30000
1$
b10010001101000101011001111000 #
b10010001101000101011001111000 *
b101 &
b101 -
0%
#35000
b10010001101000101011001111000 "
b10010001101000101011001111000 +
1%
#40000
0$
0%
#45000
b10010001101000101011001111000 1
b1110111011100100110100101110100011001010010111101110010011001010110000101100100001000000111001001100101011001110110100101110011011101000110010101110010001000000111100000110101 6
b10010001101000101011001111000 5
b10010001101000101011001111000 4
1%
#50000
1$
b11001010111111101011101010111110 #
b11001010111111101011101010111110 *
b1010 &
b1010 -
0%
#55000
b11001010111111101011101010111110 !
b11001010111111101011101010111110 ,
1%
#60000
0$
0%
#65000
b11001010111111101011101010111110 2
b111011101110010011010010111010001100101001011110111001001100101011000010110010000100000011100100110010101100111011010010111001101110100011001010111001000100000011110000011000100110000 6
b11001010111111101011101010111110 5
b11001010111111101011101010111110 4
1%
#70000
0%
#75000
b11110000011010100100000011100000111001001100101011100110110010101110010011101100110010101100100 6
b10010001101000101011001111000 5
b10010001101000101011001111000 4
1%
#80000
1$
b11111111111111111111111111111111 #
b11111111111111111111111111111111 *
b0 &
b0 -
0%
#85000
1%
#90000
b0 "
b0 +
b0 (
b0 .
0$
0%
#95000
b0 1
b11110000011000000100000011100100110010101101101011000010110100101101110011100110010000001111010011001010111001001101111 6
b0 5
b0 4
1%
#100000
1$
b11011110101011011011111011101111 #
b11011110101011011011111011101111 *
b101 &
b101 -
0%
#105000
1%
#110000
b11011110101011011011111011101111 "
b11011110101011011011111011101111 +
b101 (
b101 .
0$
0%
#115000
b11011110101011011011111011101111 1
b11011110111011001100101011100100111011101110010011010010111010001100101001000000111100000110101 6
b11011110101011011011111011101111 5
b11011110101011011011111011101111 4
1%
#120000
1'
0%
#125000
b0 !
b0 ,
b0 "
b0 +
b100000 0
1%
#130000
0'
0%
#135000
b0 2
b0 1
b1110010011001010111001101100101011101000010000001100011011011000110010101100001011100100111001100100000011110000011000100110000 6
b0 5
b0 4
1%
