synthesis/bitEXT.sv
module bitEXT(
    input  logic [31:0] Inst,
    input  logic [1:0]  IMMtype,
    
    output logic [31:0] Out
);
    reg [31:0] Immediate;
    
    assign Out = Immediate;
    case (Immtype) begin
        2'b00: begin
            Immediate = {{20{Inst[31]}}, Inst[31:20]};
        end
        2'b01: begin
            Immediate = {{20{Inst[31]}}, Inst[31:25], Inst[11:7]};
        end
        2'b10: begin
            Immediate = {{20{Inst[31]}}, Inst[31], Inst[7], Inst[30:25], Inst[11:8], 0};
        end
        2'b11: begin
            Immediate = {{12{Inst[31]}}, Inst[31:12]};
        end
    end
endmodule

synthesis/tb/tb_bitEXT.sv
`timescale 1ns/1ps

module tb_bitEXT;

    logic [31:0] Inst;
    logic [1:0]  Immtype;

    logic [31:0] Out;

    bitEXT dut (
        .Inst(Inst),
        .Immtype(Immtype),
        .Out(Out)
    );

    //----------------------------------------------------------
    // Check Task
    //----------------------------------------------------------

    task check(
        input [31:0] expected,
        input [255:0] msg
    );
    begin
        #1;
        if (Out !== expected) begin
            $display("FAIL: %s", msg);
            $display(" Expected: %h", expected);
            $display(" Got:      %h", Out);
        end
        else begin
            $display("PASS: %s", msg);
        end
    end
    endtask

    //----------------------------------------------------------
    // Test Sequence
    //----------------------------------------------------------

    initial begin

        $dumpfile("tests/bitEXT.vcd");
        $dumpvars(0, tb_bitEXT);

        //------------------------------------------------------
        // I-Type Positive Immediate
        //------------------------------------------------------

        Immtype = 2'b00;
        Inst = 32'h12345000;
        check(32'h00000123, "I-Type Positive");

        //------------------------------------------------------
        // I-Type Negative Immediate
        //------------------------------------------------------

        Immtype = 2'b00;
        Inst[31:20] = 12'hFFF;
        check(32'hFFFFFFFF, "I-Type Negative");

        //------------------------------------------------------
        // S-Type Positive Immediate
        //------------------------------------------------------

        Immtype = 2'b01;

        Inst = 32'b0;
        Inst[31:25] = 7'b0000001;
        Inst[11:7]  = 5'b00010;

        // Immediate = 000000100010 = 0x22

        check(32'h00000022, "S-Type Positive");

        //------------------------------------------------------
        // S-Type Negative Immediate
        //------------------------------------------------------

        Immtype = 2'b01;

        Inst = 32'b0;
        Inst[31] = 1'b1;
        Inst[30:25] = 6'b111111;
        Inst[11:7] = 5'b11111;

        check(32'hFFFFFFFF, "S-Type Negative (-1)");

        //------------------------------------------------------
        // B-Type Positive Immediate
        //------------------------------------------------------

        Immtype = 2'b10;

        Inst = 32'b0;

        // Immediate = 16

        Inst[11:8]  = 4'b1000;

        check(32'h00000010, "B-Type Positive");

        //------------------------------------------------------
        // B-Type Negative Immediate
        //------------------------------------------------------

        Immtype = 2'b10;

        Inst = 32'b0;

        Inst[31]    = 1;
        Inst[7]     = 1;
        Inst[30:25] = 6'b111111;
        Inst[11:8]  = 4'b1111;

        check(32'hFFFFFFFE, "B-Type Negative (-2)");

        //------------------------------------------------------
        // U-Type Positive Immediate
        //------------------------------------------------------

        Immtype = 2'b11;

        Inst = 32'h12345000;

        check(32'h00012345, "U-Type Positive");

        //------------------------------------------------------
        // U-Type Negative Immediate
        //------------------------------------------------------

        Immtype = 2'b11;

        Inst = 32'hF2345000;

        check(32'h000F2345, "U-Type Negative");

        //------------------------------------------------------

        $display("------------------------------------");
        $display("Bit Extender tests completed.");
        $display("------------------------------------");

        #10;
        $finish;

    end

endmodule

tests/bitEXT.vcd
$date
	Fri Jul  3 00:29:33 2026
$end
$version
	Icarus Verilog
$end
$timescale
	1ps
$end
$scope module tb_bitEXT $end
$var wire 32 ! Out [31:0] $end
$var reg 2 " Immtype [1:0] $end
$var reg 32 # Inst [31:0] $end
$scope module dut $end
$var wire 2 $ Immtype [1:0] $end
$var wire 32 % Inst [31:0] $end
$var wire 32 & Out [31:0] $end
$var reg 32 ' Immediate [31:0] $end
$upscope $end
$scope task check $end
$var reg 32 ( expected [31:0] $end
$var reg 256 ) msg [255:0] $end
$upscope $end
$upscope $end
$enddefinitions $end
$comment Show the parameter values. $end
$dumpall
$end
#0
$dumpvars
b10010010010110101010100011110010111000001100101001000000101000001101111011100110110100101110100011010010111011001100101 )
b100100011 (
b100100011 '
b100100011 &
b10010001101000101000000000000 %
b0 $
b10010001101000101000000000000 #
b0 "
b100100011 !
$end
#1000
b11111111111111111111111111111111 !
b11111111111111111111111111111111 &
b11111111111111111111111111111111 '
b10010010010110101010100011110010111000001100101001000000100111001100101011001110110000101110100011010010111011001100101 )
b11111111111111111111111111111111 (
b11111111111101000101000000000000 #
b11111111111101000101000000000000 %
#2000
b100010 !
b100010 &
b100010 '
b10100110010110101010100011110010111000001100101001000000101000001101111011100110110100101110100011010010111011001100101 )
b100010 (
b10000000000000000100000000 #
b10000000000000000100000000 %
b1 "
b1 $
#3000
b11111111111111111111111111111111 !
b11111111111111111111111111111111 &
b11111111111111111111111111111111 '
b101001100101101010101000111100101110000011001010010000001001110011001010110011101100001011101000110100101110110011001010010000000101000001011010011000100101001 )
b11111111111111111111111111111111 (
b11111110000000000000111110000000 #
b11111110000000000000111110000000 %
#4000
b10000 !
b10000 &
b10000 '
b10000100010110101010100011110010111000001100101001000000101000001101111011100110110100101110100011010010111011001100101 )
b10000 (
b100000000000 #
b100000000000 %
b10 "
b10 $
#5000
b11111111111111111111111111111110 !
b11111111111111111111111111111110 &
b11111111111111111111111111111110 '
b100001000101101010101000111100101110000011001010010000001001110011001010110011101100001011101000110100101110110011001010010000000101000001011010011001000101001 )
b11111111111111111111111111111110 (
b11111110000000000000111110000000 #
b11111110000000000000111110000000 %
#6000
b10010001101000101 !
b10010001101000101 &
b10010001101000101 '
b10101010010110101010100011110010111000001100101001000000101000001101111011100110110100101110100011010010111011001100101 )
b10010001101000101 (
b10010001101000101000000000000 #
b10010001101000101000000000000 %
b11 "
b11 $
#7000
b11110010001101000101 !
b11110010001101000101 &
b11110010001101000101 '
b10101010010110101010100011110010111000001100101001000000100111001100101011001110110000101110100011010010111011001100101 )
b11110010001101000101 (
b11110010001101000101000000000000 #
b11110010001101000101000000000000 %
